lemonpdf/__init__.py
lemonpdf/__main__.py
lemonpdf/cli.py
lemonpdf/version.py
lemonpdf-2.0.0.dist-info/METADATA
lemonpdf-2.0.0.dist-info/WHEEL
lemonpdf-2.0.0.dist-info/entry_points.txt
lemonpdf-2.0.0.dist-info/top_level.txt
lemonpdf-2.0.0.dist-info/RECORD
