Metadata-Version: 2.1
Name: lemonpdf
Version: 2.0.0
Summary: Python3 library to get urls from PDF files.
Author: zudefoque
Author-email: Juan Bindez <juanbindez780@gmail.com>
License: MIT license
Project-URL: Homepage, https://github.com/juanbindez/lemonpdf
Project-URL: Bug Reports, https://github.com/juanbindez/lemonpdf/issues
Project-URL: Read the Docs, http://lemonpdf.readthedocs.io/
Keywords: PDF,Extractor,cli,tools
Classifier: Development Status :: 5 - Production/Stable
Classifier: Environment :: Console
Classifier: Intended Audience :: Developers
Classifier: License :: OSI Approved :: MIT License
Classifier: Natural Language :: English
Classifier: Operating System :: OS Independent
Classifier: Programming Language :: Python :: 3.7
Classifier: Programming Language :: Python :: 3.8
Classifier: Programming Language :: Python :: 3.9
Classifier: Programming Language :: Python :: 3.10
Classifier: Programming Language :: Python :: 3.11
Classifier: Programming Language :: Python :: 3.12
Classifier: Programming Language :: Python
Classifier: Topic :: Internet
Classifier: Topic :: Software Development :: Libraries :: Python Modules
Classifier: Topic :: Terminals
Classifier: Topic :: Utilities
Requires-Python: >=3.7
Requires-Dist: packaging
Requires-Dist: pdf2image
Requires-Dist: pillow
Requires-Dist: PyMuPDF
Requires-Dist: PyMuPDFb
Requires-Dist: pytesseract
